<?xml version="1.0" encoding="utf-8"?>
<bangdiem>
  <sinhvien masv="1111" monhoc="Lập trình Windows">
    <diemlan1>8</diemlan1>
    <diemlan2>8</diemlan2>
  </sinhvien>
  <sinhvien masv="1111" monhoc="Lập trình Windows">
    <diemlan1>9</diemlan1>
    <diemlan2>5</diemlan2>
  </sinhvien>
  <sinhvien masv="1111" monhoc="Lập trình Windows">
    <diemlan1>9</diemlan1>
    <diemlan2>5</diemlan2>
  </sinhvien>
  <sinhvien masv="1111" monhoc="Lập trình Windows">
    <diemlan1>38</diemlan1>
    <diemlan2>8</diemlan2>
  </sinhvien>
</bangdiem>